torch_tuner/__init__.py
torch_tuner-0.1.0.dist-info/METADATA
torch_tuner-0.1.0.dist-info/WHEEL
torch_tuner-0.1.0.dist-info/entry_points.txt
torch_tuner-0.1.0.dist-info/top_level.txt
torch_tuner-0.1.0.dist-info/RECORD
