Metadata-Version: 2.2
Name: torch_tuner
Version: 0.1.0
Summary: Tuning the model values and gradients using PyTorch
Author: Mritunjay
Author-email: mritunjay.1121@gmail.com
License: The Unlicense
Project-URL: Source, https://github.com/Mritunjay1121/torch-tuner
Classifier: Development Status :: 3 - Alpha
Classifier: Intended Audience :: Developers
Classifier: Programming Language :: Python :: 3.9
Classifier: Programming Language :: Python :: 3.8
Classifier: Programming Language :: Python :: 3.10
Classifier: Programming Language :: Python :: 3.11
Classifier: Topic :: Scientific/Engineering :: Artificial Intelligence
Classifier: Topic :: Software Development :: Libraries :: Python Modules
Classifier: Topic :: Utilities
Requires-Python: >=3.9,<3.12
Requires-Dist: pathlib
Requires-Dist: setuptools
Dynamic: author
Dynamic: author-email
Dynamic: classifier
Dynamic: description
Dynamic: description-content-type
Dynamic: license
Dynamic: project-url
Dynamic: requires-dist
Dynamic: requires-python
Dynamic: summary
